filecaching/__init__.py
filecaching-0.0.4.dist-info/licenses/LICENSE
filecaching-0.0.4.dist-info/METADATA
filecaching-0.0.4.dist-info/WHEEL
filecaching-0.0.4.dist-info/top_level.txt
filecaching-0.0.4.dist-info/RECORD
