Metadata-Version: 2.4
Name: filecaching
Version: 0.0.4
Summary: A simple and easy-to-use file caching tool
Home-page: https://github.com/jeeaay/python-file-cache.git
Author: Jeay
Author-email: wrjie@msn.cn
License: Apache-2.0 License
Keywords: filecaching,filecache,cache,file caching tool,caching
Platform: any
License-File: LICENSE
Dynamic: author
Dynamic: author-email
Dynamic: description
Dynamic: description-content-type
Dynamic: home-page
Dynamic: keywords
Dynamic: license
Dynamic: license-file
Dynamic: platform
Dynamic: summary
